{
  "id": "jswidgets.LabelFieldForm",
  "displayHint": "view",
  "rootGroupBox": {
    "id": "MainBox",
    "objectType": "GroupBox",
    "fields": [
      {
        "id": "DetailBox",
        "objectType": "GroupBox",
        "gridColumnCount": 1,
        "fields": [
          {
            "id": "LabelField",
            "objectType": "LabelField",
            "label": "Label Field",
            "value": "${textKey:LabelFieldValue}"
          }
        ]
      },
      {
        "id": "ConfigurationBox",
        "objectType": "TabBox",
        "cssClass": "jswidgets-configuration",
        "selectedTab": "PropertiesTab",
        "tabItems": [
          {
            "id": "PropertiesTab",
            "objectType": "TabItem",
            "label": "Properties",
            "fields": [
              {
                "id": "PropertiesBox",
                "objectType": "GroupBox",
                "label": "Properties",
                "labelVisible": false,
                "borderVisible": false,
                "fields": [
                  {
                    "id": "WrapTextField",
                    "objectType": "CheckBoxField",
                    "label": "Wrap Text",
                    "labelVisible": false
                  },
                  {
                    "id": "HtmlEnabledField",
                    "objectType": "CheckBoxField",
                    "label": "Html Enabled",
                    "labelVisible": false
                  }
                ]
              },
              {
                "id": "ValueFieldPropertiesBox",
                "objectType": "jswidgets.ValueFieldPropertiesBox"
              },
              {
                "id": "FormFieldPropertiesBox",
                "objectType": "jswidgets.FormFieldPropertiesBox"
              },
              {
                "id": "GridDataBox",
                "objectType": "jswidgets.GridDataBox",
                "label": "Grid Data Hints"
              }
            ]
          },
          {
            "id": "ActionsTab",
            "objectType": "TabItem",
            "label": "Actions",
            "fields": [
              {
                "id": "WidgetActionsBox",
                "objectType": "jswidgets.WidgetActionsBox"
              }
            ]
          },
          {
            "id": "EventsTab",
            "objectType": "jswidgets.EventsTab"
          }
        ]
      }
    ]
  }
}
