{
  "id": "jswidgets.RadioButtonGroupForm",
  "displayHint": "view",
  "rootGroupBox": {
    "id": "MainBox",
    "objectType": "GroupBox",
    "fields": [
      {
        "id": "DetailBox",
        "objectType": "GroupBox",
        "gridColumnCount": 1,
        "fields": [
          {
            "id": "RadioButtonGroup",
            "objectType": "RadioButtonGroup",
            "label": "Radio Button Group",
            "gridDataHints": {
              "h": 3,
              "weightY": 0
            },
            "fields": [
              {
                "id": "RadioButton1",
                "objectType": "RadioButton",
                "label": "Radio Button 1",
                "radioValue": 1
              },
              {
                "id": "RadioButton2",
                "objectType": "RadioButton",
                "label": "Radio Button 2",
                "radioValue": 2
              },
              {
                "id": "RadioButton3",
                "objectType": "RadioButton",
                "label": "Radio Button 3",
                "radioValue": 3
              }
            ]
          }
        ]
      },
      {
        "id": "ConfigurationBox",
        "objectType": "TabBox",
        "cssClass": "jswidgets-configuration",
        "selectedTab": "PropertiesTab",
        "tabItems": [
          {
            "id": "PropertiesTab",
            "objectType": "TabItem",
            "label": "Group Properties",
            "fields": [
              {
                "id": "PropertiesBox",
                "objectType": "GroupBox",
                "label": "Properties",
                "labelVisible": false,
                "borderVisible": false,
                "fields": [
                  {
                    "id": "SelectedButtonField",
                    "objectType": "SmartField",
                    "label": "Selected Button"
                  },
                  {
                    "id": "GridColumnCountField",
                    "objectType": "NumberField",
                    "label": "Grid Column Count"
                  }
                ]
              },
              {
                "id": "ValueFieldPropertiesBox",
                "objectType": "jswidgets.ValueFieldPropertiesBox"
              },
              {
                "id": "FormFieldPropertiesBox",
                "objectType": "jswidgets.FormFieldPropertiesBox"
              },
              {
                "id": "GridDataBox",
                "objectType": "jswidgets.GridDataBox",
                "label": "Grid Data Hints"
              },
              {
                "id": "LayoutConfigBox",
                "objectType": "jswidgets.LogicalGridLayoutConfigBox",
                "expanded": false
              }
            ]
          },
          {
            "id": "RadioButtonPropertiesTab",
            "objectType": "TabItem",
            "label": "Button Properties",
            "fields": [
              {
                "id": "Button.TargetField",
                "objectType": "SmartField",
                "label": "Target"
              },
              {
                "id": "Button.PropertiesBox",
                "objectType": "GroupBox",
                "label": "Properties",
                "fields": [
                  {
                    "id": "Button.KeyStrokeField",
                    "objectType": "StringField",
                    "label": "Key Stroke"
                  },
                  {
                    "id": "Button.SelectedField",
                    "objectType": "CheckBoxField",
                    "label": "Selected",
                    "labelVisible": false
                  }
                ]
              },
              {
                "id": "Button.FormFieldPropertiesBox",
                "objectType": "jswidgets.FormFieldPropertiesBox"
              },
              {
                "id": "Button.GridDataBox",
                "objectType": "jswidgets.GridDataBox",
                "label": "Grid Data Hints"
              }
            ]
          },
          {
            "id": "ActionsTab",
            "objectType": "TabItem",
            "label": "Actions",
            "fields": [
              {
                "id": "WidgetActionsBox",
                "objectType": "jswidgets.WidgetActionsBox"
              }
            ]
          },
          {
            "id": "EventsTab",
            "objectType": "jswidgets.EventsTab"
          }
        ]
      }
    ]
  }
}
